math_dioproject
