Metadata-Version: 2.1
Name: math-dioproject
Version: 0.0.4
Summary: Solve and check simple math problems
Home-page: https://github.com/marcocrippa/Calculadora_DioProject
Author: Marco Crippa
Author-email: xmarcocrippa@gmail.com
License: UNKNOWN
Platform: UNKNOWN
Requires-Python: >=3.8
